setup.py
src/redrover/__init__.py
src/redrover/base.py
src/redrover/expect.py
src/redrover/plugin.py
src/redrover/runner.py
src/redrover/subject.py
src/redrover/utils.py
src/redrover.egg-info/PKG-INFO
src/redrover.egg-info/SOURCES.txt
src/redrover.egg-info/dependency_links.txt
src/redrover.egg-info/not-zip-safe
src/redrover.egg-info/requires.txt
src/redrover.egg-info/top_level.txt
src/redrover/assertions/__init__.py
src/redrover/assertions/base.py
src/redrover/assertions/be_exactly_assertion.py
src/redrover/assertions/be_valid_assertion.py
src/redrover/assertions/contain_assertion.py
src/redrover/assertions/equal_assertion.py
src/redrover/assertions/have_selector_assertion.py
src/redrover/assertions/have_text_assertion.py
src/redrover/assertions/respond_to_assertion.py
src/redrover/expectations/__init__.py
src/redrover/expectations/base.py
src/redrover/expectations/change_expectation.py
src/redrover/management/__init__.py
src/redrover/management/commands/__init__.py
src/redrover/management/commands/test.py