Metadata-Version: 1.1
Name: redrover
Version: 0.7.7
Summary: A testing utility suite for Django.
Home-page: https://github.com/dustinfarris/redrover
Author: Dustin Farris
Author-email: dustin@dustinfarris.com
License: BSD
Platform: UNKNOWN
Classifier: Framework :: Django
Classifier: Intended Audience :: Developers
Classifier: Intended Audience :: System Administrators
Classifier: Operating System :: OS Independent
Classifier: Topic :: Software Development
